vulnguard/__init__.py
vulnguard/agents/__init__.py
vulnguard/agents/assessment.py
vulnguard/agents/base.py
vulnguard/agents/code_review.py
vulnguard/agents/orchestrator.py
vulnguard/agents/threat_modeling.py
vulnguard/cli/__init__.py
vulnguard/cli/main.py
vulnguard/models/__init__.py
vulnguard/models/issue.py
vulnguard/models/result.py
vulnguard/reporters/__init__.py
vulnguard/reporters/json_reporter.py
vulnguard/scanner/__init__.py
vulnguard/scanner/analyzer.py
vulnguard/scanner/context_gatherer.py
vulnguard-0.2.1.dist-info/METADATA
vulnguard-0.2.1.dist-info/WHEEL
vulnguard-0.2.1.dist-info/entry_points.txt
vulnguard-0.2.1.dist-info/top_level.txt
vulnguard-0.2.1.dist-info/RECORD
